cuanalytics/__init__.py
cuanalytics/formula.py
cuanalytics/neuralnet.py
cuanalytics/clustering/__init__.py
cuanalytics/clustering/hierarchical.py
cuanalytics/clustering/kmeans.py
cuanalytics/datasets/__init__.py
cuanalytics/datasets/loaders.py
cuanalytics/entropy/__init__.py
cuanalytics/entropy/metrics.py
cuanalytics/entropy/visualization.py
cuanalytics/knn/__init__.py
cuanalytics/knn/classifier.py
cuanalytics/knn/regressor.py
cuanalytics/lda/__init__.py
cuanalytics/lda/discriminant.py
cuanalytics/preprocessing/__init__.py
cuanalytics/preprocessing/scale.py
cuanalytics/preprocessing/split.py
cuanalytics/regression/__init__.py
cuanalytics/regression/linear.py
cuanalytics/regression/logistic.py
cuanalytics/similarity/__init__.py
cuanalytics/similarity/metrics.py
cuanalytics/svm/__init__.py
cuanalytics/svm/classifier.py
cuanalytics/trees/__init__.py
cuanalytics/trees/decision_tree.py
cuanalytics-0.2.1.dist-info/licenses/LICENSE
cuanalytics-0.2.1.dist-info/METADATA
cuanalytics-0.2.1.dist-info/WHEEL
cuanalytics-0.2.1.dist-info/top_level.txt
cuanalytics-0.2.1.dist-info/RECORD
