Metadata-Version: 2.4
Name: cuanalytics
Version: 0.2.1
Summary: Python toolkit for Cedarville University students studying Business Analytics
Author-email: "Dr. John D. Delano" <jdelano@cedarville.edu>
License: MIT
Project-URL: Homepage, https://github.com/jdelano/CUAnalytics
Project-URL: Documentation, https://github.com/jdelano/CUAnalytics#readme
Project-URL: Repository, https://github.com/jdelano/CUAnalytics
Project-URL: Issues, https://github.com/jdelano/CUAnalytics/issues
Keywords: analytics,machine-learning,education,data-science,business-analytics
Classifier: Programming Language :: Python :: 3
Classifier: Programming Language :: Python :: 3.9
Classifier: Programming Language :: Python :: 3.10
Classifier: Programming Language :: Python :: 3.11
Classifier: Programming Language :: Python :: 3.12
Classifier: Programming Language :: Python :: 3.13
Classifier: License :: OSI Approved :: MIT License
Classifier: Operating System :: OS Independent
Classifier: Intended Audience :: Education
Classifier: Topic :: Education
Classifier: Topic :: Scientific/Engineering
Requires-Python: >=3.9
License-File: LICENSE
Requires-Dist: numpy>=1.20.0
Requires-Dist: pandas>=1.3.0
Requires-Dist: matplotlib>=3.4.0
Requires-Dist: scipy>=1.7.0
Requires-Dist: requests>=2.25.0
Requires-Dist: scikit-learn>=1.0.0
Requires-Dist: openpyxl>=3.0.0
Requires-Dist: formulaic>=1.0.0
Provides-Extra: dev
Requires-Dist: pytest>=7.0.0; extra == "dev"
Requires-Dist: pytest-cov>=3.0.0; extra == "dev"
Requires-Dist: build>=0.10.0; extra == "dev"
Requires-Dist: twine>=4.0.0; extra == "dev"
Dynamic: license-file
